mcp_seniverse_weather_sunw/__init__.py
mcp_seniverse_weather_sunw/__main__.py
mcp_seniverse_weather_sunw/server.py
mcp_seniverse_weather_sunw-0.0.9.dist-info/METADATA
mcp_seniverse_weather_sunw-0.0.9.dist-info/WHEEL
mcp_seniverse_weather_sunw-0.0.9.dist-info/entry_points.txt
mcp_seniverse_weather_sunw-0.0.9.dist-info/RECORD
